[{"Number":"13","Song Title":"The Lord is in This Place"}
{"Number":"27","Song Title":"Bethel","lyrics":"O, for a closer walk with God!"},
{"Number":"28t","Song Title":" Will Guide Us Till We Die (Aylesbury)","lyrics":"The God we worship now"},
{"Number":"28b","Song Title":"Life Is the Time to Serve the Lord (Wells)","lyrics":"Life is the time to serve the Lord,"},
{"Number":"29t","Song Title":" Come, Humble Sinner (Fairfield)","lyrics":"Come, humble sinner, in whose breast"},
{"Number":"29b","Song Title":"Entreaty (Liverpool)","lyrics":"Young people all attention give"},
{"Number":"30t","Song Title":" Rochester","lyrics":"Come, let us join our cheerful songs"},
{"Number":"30b","Song Title":"Prospect","lyrics":"Why should we start or fear to die"},
{"Number":"31t","Song Title":"Ninety-Third Psalm","lyrics":"Grace! tis a charming sound,"},
{"Number":"31b","Song Title":"Come, We That Love the Lord (Webster)","lyrics":"Come, we that love the Lord,"},
{"Number":"32t","Song Title":" I’m Not Ashamed of Jesus (Corinth)","lyrics":"Jesus and shall it ever be,"},
{"Number":"32b","Song Title":"Weeping Saviour","lyrics":"Did Christ o’er sinners weep,"},
{"Number":"33","Song Title":"Gathering Home","lyrics":"There is a land of pure delight,"},
{"Number":"34","Song Title":"Gone to a Better World","lyrics":"Farewell, dear parents, I must go,"},
{"Number":"35","Song Title":"Augusta","lyrics":"O for a shout of sacred joy"},
{"Number":"36t","Song Title":" America","lyrics":"My soul repeat his praise,"},
{"Number":"36b","Song Title":"Ninety-Fifth Psalm","lyrics":"When I can read my title clear,"},
{"Number":"37","Song Title":"The Christian’s Home","lyrics":"Our father dear has gone to rest,"},
{"Number":"38t","Song Title":" Sessions","lyrics":"Sinner, O why so thoughtless grown"},
{"Number":"38b","Song Title":"The Road to Life and Death (Windham)","lyrics":"Broad is the road that leads to death,"},
{"Number":"39","Song Title":"Eden of Love","lyrics":"How sweet to reflect on those joys that await me,"},
{"Number":"40","Song Title":"Blow Ye the Trumpet (Lenox)","lyrics":"Blow ye the trumpet, blow,"},
{"Number":"41","Song Title":"Poyner","lyrics":"How long, dear Savior, O how long"},
{"Number":"42","Song Title":"Social Band (Clamanda)","lyrics":"Say, now ye lovely social band,"},
{"Number":"43","Song Title":"The Hope of Heaven (Primrose Hill)","lyrics":"When I can read my title clear"},
{"Number":"44","Song Title":"The Converted Thief","lyrics":"As on the cross the Savior hung,"},
{"Number":"45t","Song Title":" Amazing Grace (New Britain)","lyrics":"Amazing grace! how sweet the sound,"},
{"Number":"45b","Song Title":"Supplication","lyrics":"O thou who hear’st when sinners cry,"},
{"Number":"46","Song Title":"The Fountain of Life","lyrics":"There is a fountain filled with blood,"},
{"Number":"47t","Song Title":" Salvation, O the Joyful Sound (Primrose)","lyrics":"Salvation! O, the joyful sound!"},
{"Number":"47b","Song Title":"Idumea","lyrics":"And am I born to die"},
{"Number":"48t","Song Title":" Devotion","lyrics":"Sweet is the day of sacred rest,"},
{"Number":"48b","Song Title":"Thou Man of Grief (Kedron)","lyrics":"Thou Man of grief, remember me,"},
{"Number":"49t","Song Title":" Old Hundred","lyrics":"O come, loud anthems let us sing,"},
{"Number":"49b","Song Title":"Will God Forever Cast Us Off (Mear)","lyrics":"Will God forever cast us off"},
{"Number":"50t","Song Title":" Consolation","lyrics":"Once more, my soul, the rising day"},
{"Number":"50b","Song Title":"Distress","lyrics":"So fades the lovely blooming flow’r;"},
{"Number":"51","Song Title":"My Home (Lisbon)","lyrics":"On Jordan’s stormy banks I stand,"},
{"Number":"52t","Song Title":" Albion","lyrics":"Come, we that love the Lord,"},
{"Number":"52b","Song Title":"Prayer of Bartimeus (Charlestown)","lyrics":"Mercy, O Thou Son of David,"},
{"Number":"53","Song Title":"Jerusalem","lyrics":"Jesus, my all, to heav’n is gone,"},
{"Number":"54t","Song Title":" Palmetto","lyrics":"Sweet the moments, rich in blessing"},
{"Number":"54b","Song Title":"Farewell, My Brethren (Imandra New)","lyrics":"Farewell, my dear brethren, the time is at hand"},
{"Number":"55","Song Title":"Shall We Know Each Other There","lyrics":"When we hear the music ringing"},
{"Number":"56","Song Title":"Salem","lyrics":"How sweet the name of Jesus sounds"},
{"Number":"57","Song Title":"Am I a Soldier of the Cross (Christian Soldier)","lyrics":"Am I a soldier of the cross,"},
{"Number":"58","Song Title":"Pisgah","lyrics":"Jesus, Thou art the sinner’s friend,"},
{"Number":"59t","Song Title":" Lord Revive Us (Holy Manna)","lyrics":"Come, Thou Fount of ev’ry blessing,"},
{"Number":"59b","Song Title":"Holy Manna","lyrics":"Brethren, we have met to worship,"},
{"Number":"60","Song Title":"Saints Bound for Heaven","lyrics":"Our bondage, it shall end by and by, by and by;"},
{"Number":"61","Song Title":"Sweet Rivers","lyrics":"Sweet rivers of redeeming love"},
{"Number":"62","Song Title":"Parting Hand","lyrics":"My Christian friends, in bonds of love,"},
{"Number":"63","Song Title":"Coronation","lyrics":"All hail the pow’r of Jesus’ name,"},
{"Number":"64","Song Title":"Refreshing Showers (Nashville)","lyrics":"The Lord into His garden come,"},
{"Number":"65","Song Title":"Sweet Prospect","lyrics":"On Jordan’s stormy banks I stand,"},
{"Number":"66","Song Title":"Security","lyrics":"O for a faith that will not shrink,"},
{"Number":"67","Song Title":"Columbus","lyrics":"O once I had a glorious view"},
{"Number":"68t","Song Title":" Do Not I Love Thee (Detroit)","lyrics":"Do not I love Thee, O my Lord"},
{"Number":"68b","Song Title":"Come Holy Spirit (Abbeville)","lyrics":"Come, Holy Spirit, come"},
{"Number":"69","Song Title":"Minister’s Farewell","lyrics":"Dear friends, farewell! I do you tell,"},
{"Number":"70t","Song Title":" Gainsville","lyrics":"Lord, we come before Thee now,"},
{"Number":"70b","Song Title":"Evening","lyrics":"Softly now the light of day"},
{"Number":"71","Song Title":"My Soul Forsakes Her Vain Delight (Leander)","lyrics":"My soul forsakes her vain delight,"},
{"Number":"72","Song Title":"Firm Foundation (Bellevue)","lyrics":"How firm a foundation, ye saints of the Lord,"},
{"Number":"73t","Song Title":" Show Pity, Lord (Cusseta)","lyrics":"Show pity, Lord; O Lord, forgive,"},
{"Number":"73b","Song Title":"Soldiers of Christ (Arlington)","lyrics":"Am I a soldier of the cross,"},
{"Number":"74t","Song Title":" The Inquirer","lyrics":"I’m not ashamed to own my Lord,"},
{"Number":"74b","Song Title":"Solid Comfort (King of Peace)","lyrics":"’Tis religion that can give"},
{"Number":"75","Song Title":"I Would See Jesus","lyrics":"I would see Jesus when the flow’rs"},
{"Number":"76t","Song Title":" Holiness","lyrics":"Daniel’s wisdom may I know,"},
{"Number":"76b","Song Title":"Desire for Piety","lyrics":"’Tis my desire with God to walk"},
{"Number":"77t","Song Title":" The Child of Grace","lyrics":"How happy’s ev’ry child of grace"},
{"Number":"77b","Song Title":"The Saviour’s Word (Talbotton)","lyrics":"Hark! My soul, it is the Lord"},
{"Number":"78","Song Title":"Calvary","lyrics":"I see One hanging on the tree,"},
{"Number":"79","Song Title":"The Old Ship of Zion","lyrics":"What ship is this that will take us all home,"},
{"Number":"80t","Song Title":" Shouting Song","lyrics":"Jesus, grant us all a blessing,"},
{"Number":"80b","Song Title":"Service of the Lord","lyrics":"Farewell, vain world, I’m going home;"},
{"Number":"81","Song Title":"Jesus Is Willing (Beach Spring)","lyrics":"Come, ye sinners, poor and needy,"},
{"Number":"82","Song Title":"Bound for Canaan","lyrics":"O when shall I see Jesus,"},
{"Number":"83t","Song Title":" Vale of Sorrow","lyrics":"While in this vale of sorrow,"},
{"Number":"83b","Song Title":"The Weary Souls","lyrics":"Ye weary, heavy-laden souls,"},
{"Number":"84","Song Title":"The Crucified Saviour","lyrics":"With a Savior crucified"},
{"Number":"85","Song Title":"The Morning Trumpet","lyrics":"O when shall I see Jesus,"},
{"Number":"86","Song Title":"Guiding Spirit","lyrics":"Our life is ever on the wing,"},
{"Number":"87","Song Title":"Sweet Canaan","lyrics":"O who will come and go with me"},
{"Number":"88t","Song Title":" Done With the World","lyrics":"Jesus, my all, to Heav’n is gone"},
{"Number":"88b","Song Title":"Mount Zion","lyrics":"O for a thousand tongues to sing"},
{"Number":"89","Song Title":"The Church’s Desolation","lyrics":"Well may Thy servants mourn, my God"},
{"Number":"90","Song Title":"Arise and Pray (Look Out)","lyrics":"My breth’ren all, on you I call"},
{"Number":"91","Song Title":"Assurance","lyrics":"Now shall my soul be lifted high"},
{"Number":"92","Song Title":"The Glorious Light of Zion (Burk)","lyrics":"The glorious light of Zion"},
{"Number":"93","Song Title":"Frozen Heart","lyrics":"Lord, shed a beam of heav’nly day"},
{"Number":"94","Song Title":"My Sands of Life (Mulberry Grove)","lyrics":"My sands of life are running fast"},
{"Number":"95t","Song Title":" Farewell, Vain World","lyrics":"Farewell, vain world, I’m going home"},
{"Number":"95b","Song Title":"The Christian’s Love","lyrics":"Blest be the tie that binds"},
{"Number":"96","Song Title":"Mercy Seat","lyrics":"From ev’ry stormy wind that blows"},
{"Number":"97","Song Title":"Gone to Heaven","lyrics":"Oh, where is my father"},
{"Number":"98","Song Title":"Glory Shone Around","lyrics":"While shepherds watched their flocks by night"},
{"Number":"99","Song Title":"Gospel Trumpet","lyrics":"Hark! How the gospel trumpet sounds!"},
{"Number":"100","Song Title":"The Bower of Prayer","lyrics":"To leave my dear friends, and with neighbors to part"},
{"Number":"101t","Song Title":"Canaan’s Land","lyrics":"O for a breeze of heav’nly love"},
{"Number":"101b","Song Title":"Holy City","lyrics":"There is a holy city"},
{"Number":"102","Song Title":"Fulfillment","lyrics":"See how the Scriptures are fulfilling"},
{"Number":"103","Song Title":"Animation","lyrics":"And let this feeble body fail"},
{"Number":"104","Song Title":"The Lovely Story","lyrics":"A story most lovely I’ll tell"},
{"Number":"105t","Song Title":"Saint Paul","lyrics":"Daniel’s wisdom may I know"},
{"Number":"105b","Song Title":"Turn, Sinner, Turn","lyrics":"Today, if you will hear His voice"},
{"Number":"106","Song Title":"Ecstacy","lyrics":"O, when shall I see Jesus"},
{"Number":"107","Song Title":"Martin","lyrics":"Jesus, lover of my soul"},
{"Number":"108t","Song Title":" Weeping Sinners","lyrics":"Weeping sinners, dry your tears"},
{"Number":"108b","Song Title":"The Traveler","lyrics":"Trav’ler haste, the night comes on"},
{"Number":"109","Song Title":"Carnsville","lyrics":"I love my blessed Savior"},
{"Number":"110","Song Title":"Mount Vernon","lyrics":"What solemn sound the ear invades"},
{"Number":"111t","Song Title":"Journey Home","lyrics":"O who will come and go with me"},
{"Number":"111b","Song Title":"To Die No More","lyrics":"My heav’nly home is bright and fair"},
{"Number":"112","Song Title":"The Last Words of Copernicus","lyrics":"Ye golden lamps of heav’n, farewell"},
{"Number":"113","Song Title":"The Prodigal Son","lyrics":"Afflictions, though they seem severe"},
{"Number":"114t","Song Title":" Edmonds","lyrics":"When Adam was created"},
{"Number":"114b","Song Title":"Fallen by the Way","lyrics":"I feel I’ve fallen by the way"},
{"Number":"115","Song Title":"The Midnight Cry","lyrics":"When the midnight cry began"},
{"Number":"116","Song Title":"I Will Shout and Sing in Glory","lyrics":"O who will come and go with me"},
{"Number":"117","Song Title":"Timmons","lyrics":"Lord, Thou wilt hear me when I pray"},
{"Number":"118","Song Title":"Sounding Joy","lyrics":"Behold, the morning sun"},
{"Number":"119","Song Title":"Heaven’s My Home","lyrics":"Come, all my dear brethren, and help me to sing"},
{"Number":"120","Song Title":"The Lord Jehovah Reigns (Chambers)","lyrics":"The Lord Jehovah reigns"},
{"Number":"121","Song Title":"Florence","lyrics":"Not many years their rounds shall roll"},
{"Number":"122","Song Title":"All Is Well","lyrics":"What’s this that steals, that steals upon my frame"},
{"Number":"123t","Song Title":" The Dying Christian","lyrics":"Ye objects of sense and enjoyments of time"},
{"Number":"123b","Song Title":"Cross of Christ","lyrics":"The cross of Christ inspires my heart"},
{"Number":"124t","Song Title":" Heavenly Land","lyrics":"There is a land of pure delight"},
{"Number":"124b","Song Title":"The Dying Minister","lyrics":"The time is swiftly rolling on"},
{"Number":"125","Song Title":"Expression","lyrics":"O Jesus, my Savior, I know thou art mine"},
{"Number":"126","Song Title":"Babel’s Streams","lyrics":"By Babel’s streams we sat and wept"},
{"Number":"127","Song Title":"Green Fields","lyrics":"How tedious and tasteless the hours"},
{"Number":"128","Song Title":"The Promised Land","lyrics":"On Jordan’s stormy banks I stand"},
{"Number":"129","Song Title":"Heavenly Armor","lyrics":"And if you meet with troubles"},
{"Number":"130","Song Title":"Millennium","lyrics":"The time is soon coming, by the prophets foretold"},
{"Number":"131t","Song Title":"Messiah","lyrics":"He comes! He comes! to judge the world"},
{"Number":"131b","Song Title":"Invocation","lyrics":"Rise, my soul, and stretch thy wings"},
{"Number":"132","Song Title":"Evening Shade","lyrics":"The day is past and gone"},
{"Number":"133","Song Title":"John 4:14","lyrics":"Lord, lead me to the crystal fountain"},
{"Number":"134","Song Title":"The Christian’s Hope","lyrics":"A few more days on earth to spend"},
{"Number":"135","Song Title":"Olney","lyrics":"Come, Thou Fount of ev’ry blessing"},
{"Number":"136","Song Title":"Morality","lyrics":"While beauty and youth are in their full prime"},
{"Number":"137","Song Title":"Liberty","lyrics":"No more beneath th’ oppressive hand"},
{"Number":"138t","Song Title":" Song to the Lamb","lyrics":"Behold the glories of the Lamb"},
{"Number":"138b","Song Title":"Ogletree","lyrics":"Frequent the day of God returns"},
{"Number":"139","Song Title":"Elysian","lyrics":"Burst, ye em’rald gates, and bring"},
{"Number":"140","Song Title":"Chicago","lyrics":"Almighty Father, heav’nly King!"},
{"Number":"141","Song Title":"Complainer","lyrics":"I am a great complainer"},
{"Number":"142","Song Title":"Stratfield","lyrics":"Thro’ ev’ry age, eternal God"},
{"Number":"143","Song Title":"Playel’s Hymn Second","lyrics":"While Thee I seek, protecting pow’r"},
{"Number":"144","Song Title":"Jubilee","lyrics":"Hark! the jubilee is sounding"},
{"Number":"145t","Song Title":" Streams of Mercy (Warrenton)","lyrics":"Come, Thou Fount of ev’ry blessing"},
{"Number":"145b","Song Title":"The Child’s Prayer (Sweet Affliction)","lyrics":"In the floods of tribulation"},
{"Number":"146","Song Title":"Hallelujah","lyrics":"And let this feeble body fail"},
{"Number":"147","Song Title":"Washington","lyrics":"Dismiss us with thy blessing, Lord"},
{"Number":"148","Song Title":"Jefferson","lyrics":"Glorious things of Thee are spoken"},
{"Number":"149","Song Title":"The Trumpet","lyrics":"The chariot! the chariot! its wheels roll in fire"},
{"Number":"150","Song Title":"The Spiritual Sailor","lyrics":"The people called Christians"},
{"Number":"151","Song Title":"Symphony","lyrics":"Behold, the Judge descends, His guards are nigh"},
{"Number":"152","Song Title":"Bruce’s Address","lyrics":"Soldiers of the cross, arise!"},
{"Number":"153","Song Title":"Come and Go with Me to Heaven","lyrics":"Farewell, vain world, I’m going home"},
{"Number":"154t","Song Title":" Holy Land","lyrics":"There is a land of pure delight"},
{"Number":"154b","Song Title":"Eden","lyrics":"O land of rest! for thee I sigh"},
{"Number":"155","Song Title":"How Long, Dear Saviour (Northfield)","lyrics":"How long, dear Savior, O how long"},
{"Number":"156","Song Title":"San Diego","lyrics":"From all that’s mortal, all that’s vain"},
{"Number":"157","Song Title":"How We Grovel Here Below (Zynder-Zee)","lyrics":"Look, how we grovel here below"},
{"Number":"158","Song Title":"Funeral Thought","lyrics":"Thou art gone to the grave—but we will not deplore thee"},
{"Number":"159","Song Title":"Wondrous Love","lyrics":"What wondrous love is this O my soul! O my soul!"},
{"Number":"160","Song Title":"A Crown of Life for Me","lyrics":"O the day of joy will soon appear"},
{"Number":"161","Song Title":"Sweet Home","lyrics":"Mid scenes of confusion and creature complaints"},
{"Number":"162","Song Title":"Hark! from the Tomb (Plenary)","lyrics":"Hark! from the tomb a doleful sound"},
{"Number":"163t","Song Title":" Morning","lyrics":"He dies, the friend of sinners dies"},
{"Number":"163b","Song Title":"Marysville","lyrics":"Jesus, my all, to Heav’n is gone"},
{"Number":"164","Song Title":"Duane Street","lyrics":"A poor wayfaring man of grief"},
{"Number":"165","Song Title":"Family Bible","lyrics":"How painfully pleasing the fond recollection"},
{"Number":"166","Song Title":"Joyful","lyrics":"Am I a soldier of the cross"},
{"Number":"168","Song Title":"Cowper","lyrics":"Forgive the song that falls so low"},
{"Number":"169","Song Title":"Dartmouth","lyrics":"Come, sound His praise abroad"},
{"Number":"170","Song Title":"Exhilaration","lyrics":"O may I worthy prove to see"},
{"Number":"171","Song Title":"Exhortation","lyrics":"Lord, in the morning Thou shalt hear"},
{"Number":"172","Song Title":"Harmony","lyrics":"Wake, all ye soaring throngs and sing"},
{"Number":"173","Song Title":"To Thee Will I Direct My Prayer (Phoebus)","lyrics":"Lord, in the morning Thou shalt hear"},
{"Number":"174","Song Title":"Gospel Message","lyrics":"Have you heard the gospel message sent to us today"},
{"Number":"175","Song Title":"Star in the East","lyrics":"Hail the blest morn when the great Mediator"},
{"Number":"176t","Song Title":" Ragan","lyrics":"Farewell, vain world, I’m going home"},
{"Number":"176b","Song Title":"The Good Physician","lyrics":"How lost was my condition"},
{"Number":"177","Song Title":"Jesus Loves to Answer Prayer","lyrics":"Come, my soul, thy suit prepare"},
{"Number":"178","Song Title":"Hosanna","lyrics":"When, His salvation bringing"},
{"Number":"179","Song Title":"The Christian Warfare","lyrics":"I find myself placed in a state of probation"},
{"Number":"180","Song Title":"A Place for Children","lyrics":"There’s a place for children in the singing school"},
{"Number":"181","Song Title":"The Gospel Invitation","lyrics":"Come, sinner, to the gospel feast"},
{"Number":"182","Song Title":"Newburgh","lyrics":"Let ev’ry creature join"},
{"Number":"183","Song Title":"Arbacoochee","lyrics":"Behold the love, the generous love"},
{"Number":"184t","Song Title":" Will You Come","lyrics":"Will you come to the Saviour today"},
{"Number":"184b","Song Title":"Tribulation","lyrics":"Death, ’tis a melancholy day"},
{"Number":"185","Song Title":"Pilgrim’s Farewell","lyrics":"Farewell, farewell, farewell my friends, I must be gone"},
{"Number":"186","Song Title":"Sherburne","lyrics":"While shepherds watch’d their flocks by night"},
{"Number":"187","Song Title":"The Christian’s Race","lyrics":"Awake, my soul, in joyful songs"},
{"Number":"188","Song Title":"Spring","lyrics":"The scattered clouds are fled at last"},
{"Number":"189","Song Title":"Montgomery","lyrics":"Early, my God, without delay"},
{"Number":"191","Song Title":"Jesus Is Winning Souls (Essay)","lyrics":"See how the wicked kingdom"},
{"Number":"192","Song Title":"Schenectady","lyrics":"From all that dwell below the skies"},
{"Number":"193","Song Title":"Huntington","lyrics":"Lord, what a thoughtless wretch was I"},
{"Number":"195","Song Title":"Mars Hill Morning","lyrics":"We sing the songs of Sacred Harp"},
{"Number":"196","Song Title":"Alabama","lyrics":"Angels in shining order stand"},
{"Number":"197","Song Title":"Edwards","lyrics":"I’ll praise my Maker while I’ve breath"},
{"Number":"198","Song Title":"Jesus Saves (Raymond)","lyrics":"I know that Jesus saves me now"},
{"Number":"199","Song Title":"City of Light","lyrics":"There’s a city of light, ’mid the stars we are told"},
{"Number":"200","Song Title":"With Songs and Honors (Edom)","lyrics":"With songs and honors sounding loud,"},
{"Number":"201","Song Title":"Pilgrim","lyrics":"Come, all ye mourning pilgrims dear"},
{"Number":"202","Song Title":"New Lebanon","lyrics":"Great God, the heav’n’s well order’d frame"},
{"Number":"203","Song Title":"Florida","lyrics":"Let sinners take their course"},
{"Number":"204","Song Title":"Mission","lyrics":"Young people, all attention give"},
{"Number":"205","Song Title":"Pleasant Hill","lyrics":"Religion is the chief concern"},
{"Number":"206","Song Title":"Come, Friends, Go With Me","lyrics":"Alas! And did my Saviour bleed"},
{"Number":"207t","Song Title":" I’m On My Journey Home","lyrics":"O who will come and go with me"},
{"Number":"207b","Song Title":"Passing Away","lyrics":"And must I be to judgment bro’t"},
{"Number":"208","Song Title":"Little Songs and Little Ways (Louisiana)","lyrics":"Come, little children, now we may"},
{"Number":"209","Song Title":"Sing His Praise","lyrics":"Children of the heav’nly King"},
{"Number":"210","Song Title":"Minnesota","lyrics":"Lord, ’tis an infinite delight"},
{"Number":"211","Song Title":"Whitestown","lyrics":"Where nothing dwelt but beasts of prey"},
{"Number":"212","Song Title":"Sharon","lyrics":"How pleasant ’tis to see"},
{"Number":"213","Song Title":"The Good Old Way","lyrics":"Lift up your heads, Immanuel’s friends"},
{"Number":"214","Song Title":"Repentance","lyrics":"Oh, if my soul was formed for woe"},
{"Number":"215","Song Title":"New Topia","lyrics":"Young people all, attention give"},
{"Number":"216","Song Title":"Delight","lyrics":"No burning heats by day"},
{"Number":"217","Song Title":"Great God, Attend (Ballstown)","lyrics":"Great God, attend while Zion sings"},
{"Number":"218","Song Title":"Mount Pleasant","lyrics":"There is a house not made with hands"},
{"Number":"220","Song Title":"Mount Zion","lyrics":"The hill of Zion yields"},
{"Number":"222","Song Title":"Ocean","lyrics":"Thy works of glory mighty Lord"},
{"Number":"223","Song Title":"Portuguese Hymn","lyrics":"Hither, ye faithful, haste with songs of triumph"},
{"Number":"224","Song Title":"Save, Lord, or We Perish","lyrics":"When thro’ the torn sail the wild tempest is streaming"},
{"Number":"225t","Song Title":" Newry","lyrics":"Did Christ o’er sinners weep"},
{"Number":"225b","Song Title":"Christmas Anthem","lyrics":"O how charming"},
{"Number":"227","Song Title":"Baptismal Anthem","lyrics":"In those days came John the Baptist"},
{"Number":"229","Song Title":"The Great Roll Call","lyrics":"At the sounding of the trumpet"},
{"Number":"230","Song Title":"Reverential Anthem","lyrics":"Give unto the Lord"},
{"Number":"232","Song Title":"The Crucifixion","lyrics":"They crucified the Saviour"},
{"Number":"235","Song Title":"The Resurrection (Easter Anthem)","lyrics":"The Lord is ris’n indeed! Hallelujah!"},
{"Number":"239","Song Title":"David’s Lamentation","lyrics":"David, the king, was grieved and moved"},
{"Number":"240","Song Title":"The Christian’s Song","lyrics":"Mine eyes are now closing to rest"},
{"Number":"242","Song Title":"Newton","lyrics":"When I survey the wondrous cross"},
{"Number":"243t","Song Title":" Yarbrough","lyrics":"Blow ye the trumpet, blow"},
{"Number":"243b","Song Title":"To Thee I Call (Hingham)","lyrics":"My God, my life, my love"},
{"Number":"244","Song Title":"Joyful News (Resignation)","lyrics":"Joy to the world, the Lord is come!"},
{"Number":"245","Song Title":"Vital Spark (Claremont)","lyrics":"Vital spark of heav’nly flame"},
{"Number":"250","Song Title":"Heavenly Vision","lyrics":"I beheld, and lo, a great multitude"},
{"Number":"254","Song Title":"Rose of Sharon","lyrics":"I am the rose of Sharon, and the lily of the valley"},
{"Number":"260","Song Title":"Farewell Anthem","lyrics":"My friends, I am going a long and tedious journey"},
{"Number":"263","Song Title":"Beautiful Home","lyrics":"There’s a beautiful home where no parting is known"},
{"Number":"264t","Song Title":" Great God, Attend (Duke Street)","lyrics":"Great God! Attend to my complaint"},
{"Number":"264b","Song Title":"Hebron","lyrics":"Thus far the Lord hath led me on"},
{"Number":"265t","Song Title":" Restoration New","lyrics":"How many years has man been driv’n"},
{"Number":"265b","Song Title":"Eternal Spirit (Uxbridge)","lyrics":"Thanks to the hand that set us free"},
{"Number":"266t","Song Title":" O Happy Day (Rockingham)","lyrics":"O happy day that fix’d my choice"},
{"Number":"266b","Song Title":"Lebanon New","lyrics":"Come, sinners, to the Gospel feast"},
{"Number":"267t","Song Title":" Sacred Stream","lyrics":"There is a stream whose gentle flow"},
{"Number":"267b","Song Title":"Hedgeburg","lyrics":"Thus the Eternal Father spake"},
{"Number":"268t","Song Title":" Restoration","lyrics":"Come, Thou Fount of ev’ry blessing"},
{"Number":"268b","Song Title":"Texas","lyrics":"We seek a rest beyond the skies"},
{"Number":"269","Song Title":"Nightfall","lyrics":"Softly now the light of day"},
{"Number":"270","Song Title":"Confidence","lyrics":"Away, my unbelieving fear"},
{"Number":"271t","Song Title":"Safety","lyrics":"Am I a soldier of the cross"},
{"Number":"271b","Song Title":"Come On, My Friends","lyrics":"I long to reach the shore of bliss"},
{"Number":"272","Song Title":"Exhortation","lyrics":"Now, in the heat of youthful blood"},
{"Number":"273","Song Title":"Marthasville","lyrics":"Before the judgment bar of God"},
{"Number":"274t","Song Title":" The Golden Harp","lyrics":"Farewell, vain world, I’m going home"},
{"Number":"274b","Song Title":"Baldwin","lyrics":"That awful day will surely come"},
{"Number":"275t","Song Title":" Loving-Kindness","lyrics":"Awake, my soul, to joyful lays"},
{"Number":"275b","Song Title":"Roll On","lyrics":"Why should we start and fear to die"},
{"Number":"276","Song Title":"Bridgewater","lyrics":"From all that dwell below the skies"},
{"Number":"277","Song Title":"Antioch","lyrics":"I know that my Redeemer lives"},
{"Number":"278t","Song Title":" Sweet Heaven","lyrics":"The Lord, who built the earth and sky"},
{"Number":"278b","Song Title":"Traveling Pilgrim","lyrics":"Farewell! vain world, I’m going home"},
{"Number":"279","Song Title":"Cross for You and Me","lyrics":"Must Jesus bear the cross alone"},
{"Number":"280","Song Title":"Vain World, Be Gone (Westford)","lyrics":"Far from my thoughts, vain world, be gone"},
{"Number":"282","Song Title":"I’m Going Home","lyrics":"Farewell, vain world, I’m going home!"},
{"Number":"283t","Song Title":" How Sweet the Name (Ortonville)","lyrics":"How sweet the name of Jesus sounds"},
{"Number":"283b","Song Title":"Am I a Soldier (Ortonville)","lyrics":"Am I a soldier of the cross"},
{"Number":"284","Song Title":"The Christian’s Rest","lyrics":"O land of rest, for thee I sigh"},
{"Number":"285t","Song Title":" Arnold","lyrics":"Come, let us join our friends above"},
{"Number":"285b","Song Title":"Land of Rest","lyrics":"O land of rest, for thee I sigh"},
{"Number":"286t","Song Title":" Saint’s Request","lyrics":"Young people, all attention give"},
{"Number":"286b","Song Title":"Melody","lyrics":"And must I be to judgment bro’t"},
{"Number":"287","Song Title":"Cambridge","lyrics":"The Lord will happiness divine"},
{"Number":"288","Song Title":"White","lyrics":"Ye fleeting charms of earth farewell"},
{"Number":"289","Song Title":"Greensborough","lyrics":"There is a land of pure delight"},
{"Number":"290","Song Title":"Alas! And Did My Saviour Bleed (Victoria)","lyrics":"Alas! And did my Saviour bleed"},
{"Number":"291","Song Title":"Shepherds, Rejoice","lyrics":"Shepherds, rejoice, lift up your eyes"},
{"Number":"292t","Song Title":" Happy Day","lyrics":"Blest is the man who shuns the place"},
{"Number":"292b","Song Title":"The Wonder","lyrics":"O ’tis a glorious mystery"},
{"Number":"293t","Song Title":" Ballerma","lyrics":"There is a land of pure delight"},
{"Number":"293b","Song Title":"Saint Thomas","lyrics":"Come, sound his praise abroad"},
{"Number":"294","Song Title":"Never Part","lyrics":"Come, humble sinner, in whose breast"},
{"Number":"295","Song Title":"The Sinner Must Be Born Again (Ganges)","lyrics":"Awaked by Sinai’s awful sound"},
{"Number":"296","Song Title":"Sardinia","lyrics":"Behold the love, the gen’rous love"},
{"Number":"297","Song Title":"Conversion","lyrics":"When God revealed His gracious name"},
{"Number":"298","Song Title":"Providence","lyrics":"What shall I render to my God"},
{"Number":"299","Song Title":"New Jerusalem","lyrics":"Lo! What a glorious sight appears"},
{"Number":"300","Song Title":"Calvary","lyrics":"My thoughts that often mount the skies"},
{"Number":"301","Song Title":"God’s Promise","lyrics":"There is a thought that comes to me"},
{"Number":"302","Song Title":"Greenland","lyrics":"With songs and honors sounding loud,"},
{"Number":"303","Song Title":"The Fountain (Sincerity)","lyrics":"How firm a foundation, ye saints of the Lord"},
{"Number":"304","Song Title":"Morgan","lyrics":"With songs and honors sounding loud,"},
{"Number":"306","Song Title":"News From the Regions of the Skies (Oxford)","lyrics":"Shepherds, rejoice! Lift up your eyes"},
{"Number":"308","Song Title":"Parting Friends","lyrics":"What is there here to court my stay"},
{"Number":"309","Song Title":"Living Lamb","lyrics":"Am I a soldier of the cross"},
{"Number":"310","Song Title":"The Weeping Saviour","lyrics":"Alas! and did my Savior bleed"},
{"Number":"311","Song Title":"Silver Street","lyrics":"Come, sound His praise abroad"},
{"Number":"312","Song Title":"Sing to Me of Heaven","lyrics":"O, sing to me of heav'n"},
{"Number":"313","Song Title":"Concord","lyrics":"The men of grace have found"},
{"Number":"314","Song Title":"Amherst","lyrics":"Lord of the worlds above"},
{"Number":"315","Song Title":"Worlds Above","lyrics":"Lord of the worlds above"},
{"Number":"316","Song Title":"Blessed Thought","lyrics":"We have our trials here below"},
{"Number":"318","Song Title":"Morning Meditation","lyrics":"Though the morn may seem serene"},
{"Number":"319","Song Title":"Religion Is a Fortune","lyrics":"O when shall I see Jesus"},
{"Number":"320","Song Title":"The Lost City","lyrics":"Oh, when shall I see Jesus"},
{"Number":"321","Song Title":"Man’s Redemption","lyrics":"The glorious plan of man’s redemption"},
{"Number":"322","Song Title":"Soon We Shall Land on Canaan’s Shore (Autauga)","lyrics":"Oh, when shall I see Jesus"},
{"Number":"323t","Song Title":" Mullins","lyrics":"Jesus, grant us all a blessing"},
{"Number":"323b","Song Title":"Soft Music","lyrics":"Soft, soft, music is stealing"},
{"Number":"324","Song Title":"Northport","lyrics":"Jesus, my all, to heav'n is gone"},
{"Number":"325","Song Title":"The Cause of Christ","lyrics":"Who the cause of Christ would yield"},
{"Number":"326","Song Title":"Weary Pilgrim","lyrics":"Come and taste along with me"},
{"Number":"327","Song Title":"Hatfield","lyrics":"Naked as from the earth we came"},
{"Number":"328","Song Title":"There’s a Great Day Coming","lyrics":"There’s a great day coming"},
{"Number":"329","Song Title":"Vain World, Adieu!","lyrics":"When for eternal worlds we steer"},
{"Number":"330t","Song Title":" Love Divine","lyrics":"Love divine, all love excelling,"},
{"Number":"330b","Song Title":"Sacred Music","lyrics":"In the floods of tribulation,"},
{"Number":"331t","Song Title":"The Father’s Boundless Love (Columbiana)","lyrics":"May the grace of Christ our Saviour,"},
{"Number":"331b","Song Title":"Mercy, O Thou Son of David (Villulia)","lyrics":"Mercy, O Thou Son of David,"},
{"Number":"332","Song Title":"Sons of Sorrow","lyrics":"Hail! ye sighing sons of sorrow,"},
{"Number":"333","Song Title":"Family Circle","lyrics":"Come, thou Fount of ev'ry blessing,"},
{"Number":"334","Song Title":"O Come Away!","lyrics":"O come, come away"},
{"Number":"335","Song Title":"Return Again","lyrics":"Saviour, visit Thy plantation,"},
{"Number":"336t","Song Title":" Hester","lyrics":"I love to see the Lord below,"},
{"Number":"336b","Song Title":"Haw Ridge","lyrics":"Father to Thee my soul I lift:"},
{"Number":"337","Song Title":"Mercy’s Free","lyrics":"What's this that in my soul that's rising"},
{"Number":"338","Song Title":"Rise to the Mansions of Glory","lyrics":"How bright is the day when the Christian"},
{"Number":"339","Song Title":"When I Am Gone","lyrics":"Shed not a tear o'er your friend's early bier"},
{"Number":"340","Song Title":"The Rock That Is Higher Than I","lyrics":"Convinced as a sinner to Jesus I come,"},
{"Number":"341","Song Title":"The Lone Pilgrim (The White Pilgrim)","lyrics":"I came to the place where the lone pilgrim lay,"},
{"Number":"342","Song Title":"Fountain of Life","lyrics":"There is a fountain filled with blood"},
{"Number":"343","Song Title":"Long Sought Home","lyrics":"Jerusalem! My happy home!"},
{"Number":"344","Song Title":"We’ll Meet Beyond the Grave","lyrics":"Beyond the golden sunset sky,"},
{"Number":"345t","Song Title":" Jesus Is My Friend","lyrics":"Come life, come death, come then what will,"},
{"Number":"345b","Song Title":"We’ll Meet Over There (Golden Streets)","lyrics":"And we'll meet our fathers there"},
{"Number":"346","Song Title":"My Happy Home","lyrics":"I have a home above the starry skies,"},
{"Number":"347","Song Title":"It Is a Wonder If I Am Saved (’Tis Wonder)","lyrics":"O ’tis a glorious mystery,"},
{"Number":"348t","Song Title":" Happy Land","lyrics":"There is a happy land,"},
{"Number":"348b","Song Title":"Blessed Forever","lyrics":"I sometimes think it’s too good to be true,"},
{"Number":"350","Song Title":"The Red Sea Anthem","lyrics":"The Lord spoke unto Moses saying,"},
{"Number":"355","Song Title":"Hinder Me Not","lyrics":"In all my Lord’s appointed ways"},
{"Number":"356","Song Title":"Cheves","lyrics":"Grace, 'tis a most delightful theme,"},
{"Number":"357","Song Title":"God’s Eternal (Complaint)","lyrics":"Spare us, O Lord, aloud we cry,"},
{"Number":"358","Song Title":"Murillo’s Lesson","lyrics":"As down a lone valley with cedars o'erspread,"},
{"Number":"359","Song Title":"Prosperity","lyrics":"O may I worthy prove to see,"},
{"Number":"360","Song Title":"The Royal Band","lyrics":"Hosanna to Jesus, my soul’s filled with praises,"},
{"Number":"361","Song Title":"Loving Jesus","lyrics":"Here’s my heart, my loving Jesus,"},
{"Number":"362","Song Title":"The Lord’s Promise","lyrics":"Amazing grace! How sweet the sound,"},
{"Number":"363","Song Title":"I Have No Mother Now","lyrics":"I hear the soft winds sighing"},
{"Number":"364","Song Title":"Greenland","lyrics":"Why should I be affrighted"},
{"Number":"365","Song Title":"Southwell","lyrics":"’Tis finished, the Redeemer said,"},
{"Number":"367","Song Title":"Dear Name! The Rock on Which I Stand","lyrics":"How sweet the name of Jesus sounds"},
{"Number":"368t","Song Title":" Remember Me","lyrics":"There is a fountain filled with blood,"},
{"Number":"368b","Song Title":"Newman","lyrics":"Vain man, thy found pursuits forbear,"},
{"Number":"369","Song Title":"Send a Blessing","lyrics":"O tell me no more of this world’s vain store,"},
{"Number":"370","Song Title":"Monroe","lyrics":"Jesus, I my cross have taken"},
{"Number":"371","Song Title":"Heavenly Dove (Turner)","lyrics":"Come, Holy Spirit, heavn’ly Dove"},
{"Number":"372","Song Title":"Mount Pleasant","lyrics":"There is a home not made with hands"},
{"Number":"373","Song Title":"Weeping Peter","lyrics":"Jesus, let Thy pitying eye"},
{"Number":"374","Song Title":"O Sing With Me!","lyrics":"Oh! sing with me in social spheres"},
{"Number":"375","Song Title":"Love the Lord","lyrics":"Alas! And did my Saviour bleed"},
{"Number":"376","Song Title":"Help Me to Sing","lyrics":"Ye souls, who are bound unto Canaan"},
{"Number":"377t","Song Title":" Happy Home","lyrics":"O yes, my Savior I will trust"},
{"Number":"377b","Song Title":"Parting Friends","lyrics":"The time will come when we must part"},
{"Number":"378t","Song Title":" The Heavenly Port","lyrics":"On Jordan’s stormy banks I stand"},
{"Number":"378b","Song Title":"Eureka","lyrics":"Soon will this mortal life be o’er"},
{"Number":"379","Song Title":"Span of Life","lyrics":"My span of life will soon be gone"},
{"Number":"380t","Song Title":" Nettie","lyrics":"While trav’ling thru this world below"},
{"Number":"380b","Song Title":"Humble Pleadings","lyrics":"Oh Lord, look down from Thy throne"},
{"Number":"381t","Song Title":"Never Turn Back","lyrics":"When to that blessed world I rise"},
{"Number":"381b","Song Title":"The Surrender","lyrics":"Welcome, welcome dear Redeemer"},
{"Number":"382","Song Title":"The Cleansing Fountain","lyrics":"There is a fountain flowing free"},
{"Number":"383","Song Title":"Eternal Day","lyrics":"O what of all my suff’rings here"},
{"Number":"384","Song Title":"Longing for Heaven (Panting for Heaven)","lyrics":"O when will the period appear"},
{"Number":"385t","Song Title":" Fight On","lyrics":"Fight on, my soul, till death"},
{"Number":"385b","Song Title":"Asleep in Jesus","lyrics":"Asleep in Jesus! blessed sleep,"},
{"Number":"386","Song Title":"Carry Me Home","lyrics":"Sweet land of rest! For thee I sigh"},
{"Number":"387","Song Title":"Penick","lyrics":"While trav’ling thro’ the world below"},
{"Number":"388","Song Title":"The Happy Sailor","lyrics":"Come tell of your ship and what is her name"},
{"Number":"389t","Song Title":" Saint Peters","lyrics":"How shall a lost sinner in pain"},
{"Number":"389b","Song Title":"The Sky","lyrics":"Loud swell the pealing organ’s notes"},
{"Number":"390","Song Title":"New Prospect","lyrics":"O land of rest! For thee I sigh"},
{"Number":"391","Song Title":"The Royal Invitation","lyrics":"Come, sinner, come, and help bear the cross"},
{"Number":"392","Song Title":"Little Pilgrim","lyrics":"Come little pilgrim take my hand"},
{"Number":"393","Song Title":"I’m Wandering To and Fro","lyrics":"I’m wand’ring to and fro"},
{"Number":"394","Song Title":"Messiah’s Praise","lyrics":"My heart and voice I raise"},
{"Number":"395t","Song Title":" Can I Leave You","lyrics":"Yes, my native land, I love thee"},
{"Number":"395b","Song Title":"Fleeting Days","lyrics":"Time! what an empty vapor ’tis!"},
{"Number":"396","Song Title":"Look to Jesus, Weary One","lyrics":"Haste, O sinner, now be wise"},
{"Number":"397","Song Title":"We’ll Soon Be There","lyrics":"O who will come and go with me"},
{"Number":"398t","Song Title":" Farewell to All","lyrics":"And now my friends, both old and young"},
{"Number":"398b","Song Title":"The Dying Californian","lyrics":"Lay up nearer, brother, nearer"},
{"Number":"399","Song Title":"The Dying Boy","lyrics":"I’m dying, mother, dying now"},
{"Number":"400","Song Title":"Struggle On","lyrics":"Our praying time will soon be o'er, Hallelujah!"},
{"Number":"401","Song Title":"Cuba","lyrics":"Go, preachers, and tell it to the world"},
{"Number":"402","Song Title":"Protection","lyrics":"The Lord my pasture shall prepare"},
{"Number":"403","Song Title":"Heavenly Rest","lyrics":"How happy are the souls above"},
{"Number":"404","Song Title":"He Died on the Cross","lyrics":"Jesus came to save poor sinners"},
{"Number":"405","Song Title":"Children of the Heavenly King (The Marcellas)","lyrics":"Children of the heav'nly King"},
{"Number":"406","Song Title":"New Harmony","lyrics":"I want to live a Christian here"},
{"Number":"407","Song Title":"Charlton","lyrics":"My span of life will soon be done"},
{"Number":"408","Song Title":"Weeping Mary","lyrics":"They crucified the Saviour"},
{"Number":"409","Song Title":"Promised Day","lyrics":"How long, dear Saviour, O how long"},
{"Number":"410","Song Title":"Willie","lyrics":"There’s not a bright and beaming smile"},
{"Number":"411","Song Title":"The Finest Flower","lyrics":"The finest flow’r that e’er was known"},
{"Number":"412","Song Title":"New Hosanna","lyrics":"Wake, O my soul, and hail the morn"},
{"Number":"413","Song Title":"The Loved Ones","lyrics":"Be kind to thy father, for when thou wert young"},
{"Number":"414","Song Title":"Morning Sun","lyrics":"Youth, like the spring will soon be gone"},
{"Number":"416t","Song Title":" My Native Land","lyrics":"Yes, my native land, I love thee"},
{"Number":"416b","Song Title":"Vernon","lyrics":"Come, O Thou traveler unknown"},
{"Number":"417","Song Title":"Weeping Pilgrim","lyrics":"You may tell them, father"},
{"Number":"418","Song Title":"Rees","lyrics":"There is a house, not made with hands"},
{"Number":"419","Song Title":"Melancholy Day","lyrics":"Death, ’tis a melancholy day"},
{"Number":"420","Song Title":"Religion Is Sweet","lyrics":"’Tis religion that can give"},
{"Number":"421","Song Title":"Sweet Morning","lyrics":"The happy day shall soon appear"},
{"Number":"422t","Song Title":" A Song of Texas","lyrics":"Away here in Texas, the bright, Sunny South"},
{"Number":"422b","Song Title":"The Grieved Soul","lyrics":"Come my soul and let us try"},
{"Number":"423","Song Title":"Grantville","lyrics":"Should earth against my soul engage"},
{"Number":"424","Song Title":"Sweet Union","lyrics":"Awake my soul, in joyful lays, "},
{"Number":"425","Song Title":"Golden Streets","lyrics":"I am on my journey home"},
{"Number":"426t","Song Title":" Dumas","lyrics":"When we've been there ten thousand years"},
{"Number":"426b","Song Title":"The Time is Rolling On (Shiloah)","lyrics":"The time is swiftly rolling on"},
{"Number":"427","Song Title":"Babylon is Fallen","lyrics":"Hail! the day so long expected"},
{"Number":"428","Song Title":"World Unknown","lyrics":"And am I born to die"},
{"Number":"429","Song Title":"Christian’s Delight","lyrics":"Peace, troubled soul, thou need not fear"},
{"Number":"430","Song Title":"Land of Rest","lyrics":"O land of rest, for thee I sigh"},
{"Number":"431","Song Title":"New Bethany","lyrics":"Ere mountains reared their forms sublime"},
{"Number":"432","Song Title":"The Heavenly Mansion","lyrics":"My heav'nly home is bright and fair"},
{"Number":"433","Song Title":"Rejoice","lyrics":"Shepherds, rejoice, lift up your eyes"},
{"Number":"434","Song Title":"Thus Will I Sing (Fillmore)","lyrics":"Great God, let all my tuneful pow'rs"},
{"Number":"435","Song Title":"Sacred Rest","lyrics":"Sweet is the day of sacred rest"},
{"Number":"436t","Song Title":" Humble Penitent","lyrics":"Just as I am without one plea"},
{"Number":"436b","Song Title":"The Infant Request","lyrics":"For just before the fatal hour"},
{"Number":"437","Song Title":"Ester","lyrics":"Young ladies, all attention give"},
{"Number":"438t","Song Title":" Missouri","lyrics":"O land of rest, for thee I sigh"},
{"Number":"438b","Song Title":"Jewett","lyrics":"Amazing grace, how sweet the sound"},
{"Number":"439","Song Title":"Adoration","lyrics":"Lord, when my raptured tho't surveys"},
{"Number":"440t","Song Title":" Shady Grove","lyrics":"O how stupendous was the pow'r"},
{"Number":"440b","Song Title":"Sharpsburg","lyrics":"Blest Jesus, while in mortal flesh"},
{"Number":"441","Song Title":"The Saint’s Delight","lyrics":"When I can read my title clear"},
{"Number":"442t","Song Title":" Blooming Youth","lyrics":"In the bright season of thy youth"},
{"Number":"442b","Song Title":"Pickard’s Hymn","lyrics":"In vain my fancy tries to paint"},
{"Number":"443","Song Title":"Beatrice","lyrics":"O that I knew the secret place"},
{"Number":"444t","Song Title":" The Gospel Pool","lyrics":"Beside the gospel pool"},
{"Number":"444b","Song Title":"The Teacher’s Farewell","lyrics":"Our school now closes out"},
{"Number":"445t","Song Title":" Hill of Zion","lyrics":"The hill of Zion yields"},
{"Number":"445b","Song Title":"My Last Moments","lyrics":"When the last moments come"},
{"Number":"446t","Song Title":" Sharon’s Lovely Rose","lyrics":"In Sharon's lovely rose"},
{"Number":"446b","Song Title":"Charming Sound","lyrics":"Grace! 'tis a charming sound"},
{"Number":"447t","Song Title":" Boylston","lyrics":"My God, my Life, my Love"},
{"Number":"447b","Song Title":"Laban","lyrics":"My soul, be on thy guard"},
{"Number":"448","Song Title":"I Love Thy Kingdon","lyrics":"I love Thy kingdom, Lord"},
{"Number":"449","Song Title":"Beautiful River","lyrics":"Shall we gather at the river"},
{"Number":"450","Song Title":"Leaning on Jesus’ Breast","lyrics":"O that my Lord would come and meet,"},
{"Number":"451","Song Title":"Rock of Ages (Toplady)","lyrics":"Rock of Ages, cleft for me"},
{"Number":"452","Song Title":"Elder","lyrics":"Gently glides the stream of life"},
{"Number":"453t","Song Title":" Clark","lyrics":"I know that my Redeemer lives"},
{"Number":"453b","Song Title":"Highlands of Heaven","lyrics":"Sinner go, will you go"},
{"Number":"454","Song Title":"The Blessed Lamb","lyrics":"See the happy spirits waiting"},
{"Number":"455t","Song Title":" Vesper","lyrics":"Saviour, tender Shepherd, hear me"},
{"Number":"455b","Song Title":"Still Better","lyrics":"Teach me how to do my duty"},
{"Number":"456","Song Title":"Almighty Father","lyrics":"Up to Thee, Almighty Father"},
{"Number":"457","Song Title":"Zion’s Ship","lyrics":"Come thou Fount of ev'ry blessing"},
{"Number":"458","Song Title":"Friendship","lyrics":"Mercy, O Thou son of David,"},
{"Number":"459","Song Title":"Tolling Bell","lyrics":"Shed not a tear o'er your friend's early bier"},
{"Number":"460","Song Title":"My Soul Abounds with Joy","lyrics":"While trav'ling thro' this world below"},
{"Number":"461","Song Title":"Let Us Sing","lyrics":"Shall we ever meet again at the house"},
{"Number":"462","Song Title":"Fatherland","lyrics":"There is a place where my hopes are stayed"},
{"Number":"463","Song Title":"Angel Band (Land of Beulah)","lyrics":"My latest sun is sinking fast"},
{"Number":"464","Song Title":"Hocutt","lyrics":"When Christ the Lord was crucified"},
{"Number":"465","Song Title":"Trusting","lyrics":"E're since I knew His wond'rous love"},
{"Number":"466","Song Title":"The Christian’s Flight","lyrics":"Not many years their rounds shall roll"},
{"Number":"467","Song Title":"Pray, Brethren, Pray","lyrics":"Pray, brethren, pray"},
{"Number":"468","Song Title":"Sweet Thought","lyrics":"How sweet to think He died for me"},
{"Number":"469","Song Title":"Winning Souls","lyrics":"See how the wicked kingdom"},
{"Number":"470","Song Title":"There We Our Jesus Shall Adore (Sardis)","lyrics":"Come on, my fellow pilgrims, come"},
{"Number":"471","Song Title":"Come On, My Fellow Pilgrims","lyrics":"Come on, my fellow pilgrims, come"},
{"Number":"472","Song Title":"The Sinner’s Friend","lyrics":"He dies! The friend of sinners dies"},
{"Number":"473","Song Title":"Jesus Rose","lyrics":"Go and tell his disciples"},
{"Number":"474","Song Title":"Rest for the Weary","lyrics":"Come Thou Fount of ev'ry blessing"},
{"Number":"475","Song Title":"Lover of the Lord","lyrics":"Lovers of pleasure more than God"},
{"Number":"476","Song Title":"At the Golden Gates","lyrics":"At the golden gates of glory"},
{"Number":"477","Song Title":"Let the Saints Appear","lyrics":"With rev'rence let the saints appear"},
{"Number":"478","Song Title":"March On","lyrics":"On Jordan's stormy banks I stand"},
{"Number":"479","Song Title":"Behold A Sinner","lyrics":"Behold a sinner dearest Lord"},
{"Number":"480","Song Title":"Leaning on Jesus’ Breast No 2","lyrics":"Oh if my Lord would come and meet"},
{"Number":"482","Song Title":"Amazing Love","lyrics":"When Jesus for His people died"},
{"Number":"483","Song Title":"Where the Saints Are Passing Over","lyrics":"Only just across the river"},
{"Number":"484","Song Title":"My Country ’Tis of Thee (America)","lyrics":"My country, ’tis of thee"},
{"Number":"485","Song Title":"Christ Jesus Died for Sinners","lyrics":"There’s a wonderful theme in the gospel tongue"},
{"Number":"486","Song Title":"No Night on That Golden Shore","lyrics":"O when shall we sweetly remove"},
{"Number":"488","Song Title":"Unity","lyrics":"Firmly, brethren, firmly stand"},
{"Number":"489","Song Title":"Cooper (Jordan)","lyrics":"There is a land of pure delight"},
{"Number":"490","Song Title":"Canaan’s Peaceful Shore","lyrics":"I'm on my journey home"},
{"Number":"491","Song Title":"Closer Walk With God","lyrics":"O for a closer walk with God"},
{"Number":"492","Song Title":"The Poor, Wayfaring Stranger (Wayfaring Stranger)","lyrics":"I am a poor, wayfaring stranger"},
{"Number":"493","Song Title":"Where Heavenly Joy Imparts","lyrics":"O what amazing words of grace"},
{"Number":"494","Song Title":"If Christ Be in My Arms (Grafton)","lyrics":"Jesus the vision of Thy face"},
{"Number":"495","Song Title":"A Nearness to God (Eliza)","lyrics":"O could I find from day to day"},
{"Number":"496t","Song Title":" We Shall Meet Again","lyrics":"Come, Holy Spirit, now impart"},
{"Number":"496b","Song Title":"The Master’s Call","lyrics":"My Master calls, and I must go"},
{"Number":"497","Song Title":"The Bitter Cup","lyrics":"Father, remove this bitter cup"},
{"Number":"498","Song Title":"The Living Stone","lyrics":"See what a living stone"},
{"Number":"499","Song Title":"Where Love In Glory Shines","lyrics":"God, in the gospel of His Son"},
{"Number":"500","Song Title":"Sweet By and By","lyrics":"There’s a land that is fairer than day"},
{"Number":"501","Song Title":"That Beautiful Land","lyrics":"There’s a beautiful land far beyond the sky"},
{"Number":"502","Song Title":"Wilson","lyrics":"How happy are the souls above"},
{"Number":"503","Song Title":"That Beautiful Land On High","lyrics":"There’s a beautiful land on high"},
{"Number":"504t","Song Title":" Peterborough","lyrics":"Approach, my soul, the mercy-seat"},
{"Number":"504b","Song Title":"North Jersey","lyrics":"See the leaves around ye falling"},
{"Number":"505","Song Title":"Cleansing Fountain","lyrics":"There is a fountain filled with blood"},
{"Number":"506","Song Title":"The Orphan Girl","lyrics":"“No home, no home,” plead a little girl"},
{"Number":"507t","Song Title":" Jackson","lyrics":"I am a stranger here below"},
{"Number":"507b","Song Title":"The Glory of the Cross","lyrics":"I'm not ashamed to own my Lord"},
{"Number":"508","Song Title":"Amsterdam","lyrics":"Rise my soul, and stretch thy wings"},
{"Number":"509","Song Title":"We Are Going Home","lyrics":"When I am called by death to go"},
{"Number":"510","Song Title":"Miller","lyrics":"Jesus paid the debt on Calvary, "},
{"Number":"511t","Song Title":"Brown","lyrics":"I love to steal a while away "},
{"Number":"511b","Song Title":"Jesus Died for Me","lyrics":"When e'er I cross the stream of death"},
{"Number":"512","Song Title":"Oh, How Wonderful!","lyrics":"My God is real, Oh, yes, He's real, "},
{"Number":"513t","Song Title":" The Christian’s Desire (Avon)","lyrics":"Oh, for a closer walk with God!"},
{"Number":"513b","Song Title":"Whosoever Will","lyrics":"O what amazing words of grace"},
{"Number":"514","Song Title":"Wiley","lyrics":"Dear brethren, I have found"},
{"Number":"515","Song Title":"When the Lord Shall Come for Me","lyrics":"O the night of time shall soon pass away"},
{"Number":"516","Song Title":"Tallahassee","lyrics":"Spirit Divine, attend our pray’rs"},
{"Number":"517","Song Title":"We’ll Wear a Crown","lyrics":"The Savior stands and pleads for thee"},
{"Number":"518","Song Title":"Love At Home","lyrics":"There is beauty all around"},
{"Number":"519","Song Title":"My Mother’s Gone","lyrics":"I have a father way in glory"},
{"Number":"520","Song Title":"Rest for the Soul","lyrics":"Stand ye in the way, and see, and ask"},
{"Number":"521","Song Title":"A Golden Crown to Wear","lyrics":"Life's sun is sinking down"},
{"Number":"522","Song Title":"Shades of Night","lyrics":"The shades of night are drawing near"},
{"Number":"524","Song Title":"My Home Above","lyrics":"While tenting here I have no home"},
{"Number":"526","Song Title":"Heavenly Joy","lyrics":"There’ll be joy in heaven when we reach that land"},
{"Number":"527","Song Title":"Heavenly Grace","lyrics":"Lord, when together here we meet"},
{"Number":"528t","Song Title":" The Gospel Sound","lyrics":"Go forth, ye heralds, in My Name"},
{"Number":"528b","Song Title":"Peaceful Shore","lyrics":"A few more days on earth to spend"},
{"Number":"529","Song Title":"When Jesus Calls","lyrics":"When Jesus calls me I must go"},
{"Number":"530","Song Title":"God’s Unchanging Hand","lyrics":"Thro’ a sinful world I journey"},
{"Number":"532","Song Title":"O Jesus, Ever with Us Stay","lyrics":"Jesus, and shall it ever be"},
{"Number":"533","Song Title":"Thy Love Proclaim","lyrics":"Weak is the effort of my heart"},
{"Number":"534","Song Title":"The Saints Will Be Gathered There","lyrics":"I want my friends to go with me"},
{"Number":"535t","Song Title":" Kelley","lyrics":"My Christian friends to whom I speak"},
{"Number":"535b","Song Title":"Take Me Home","lyrics":"My life on earth is out"},
{"Number":"536","Song Title":"Thy Love (North Salem)","lyrics":"Talk with us, Lord, Thyself reveal"},
{"Number":"537","Song Title":"Praise the Lord","lyrics":"I am walking with my Saviour ev'ry day"},
{"Number":"538","Song Title":"Praising Jesus","lyrics":"Come dear brethren, praise your Jesus"},
{"Number":"539","Song Title":"Bidding Farewell to Loved Ones","lyrics":"Farewell dear brothers, fare you well"},
{"Number":"540","Song Title":"She Is Sleeping","lyrics":"There’s a land beyond the river"},
{"Number":"541","Song Title":"I’m Going Home to Die No More","lyrics":"Why should we start or fear to die"},
{"Number":"542","Song Title":"The Judgment Day","lyrics":"Are you ready for the day"},
{"Number":"543","Song Title":"Consecration","lyrics":"There then to Thee Thine own I leave"},
{"Number":"544","Song Title":"My Eternal Home (Home)","lyrics":"My Father's house on high"},
{"Number":"545","Song Title":"I Have a Precious Friend","lyrics":"I need not feel one anxious thought"},
{"Number":"546","Song Title":"Farther On","lyrics":"Dark and stormy is the desert"},
{"Number":"547","Song Title":"All Is Peace and Love","lyrics":"We have our troubles here below"},
{"Number":"548","Song Title":"The God of Love","lyrics":"To thee the gracious Lord and King"},
{"Number":"549","Song Title":"That Sweet Home","lyrics":"When we have crossed the stream of death"},
{"Number":"550","Song Title":"Gone Home","lyrics":"Oh, where is now our brother dear"},
{"Number":"551","Song Title":"World Above","lyrics":"There is a holy city"},
{"Number":"552","Song Title":"And Live Through Endless Day","lyrics":"Should earth against my soul engage"},
{"Number":"553","Song Title":"The Hill of Zion","lyrics":"The hill of Zion yields"},
{"Number":"554","Song Title":"Where the Soul Shall Never Die","lyrics":"Our mother's gone to heaven"},
{"Number":"555","Song Title":"Praise the Redeemer (New Hope)","lyrics":"From all that dwell below the skies"},
{"Number":"556","Song Title":"A Prayerful Heart","lyrics":"O, for a heart to praise my God"},
{"Number":"557","Song Title":"Jordan’s Banks","lyrics":"On Jordan's stormy banks I stand"},
{"Number":"558","Song Title":"I’ll Praise My Master","lyrics":"I'll praise my Master while I've breath"},
{"Number":"559","Song Title":"Will You Meet Me","lyrics":"I am going home today"},
{"Number":"560","Song Title":"Singing As I Go","lyrics":"My life flows on in endless song"},
{"Number":"561","Song Title":"Calling Me","lyrics":"Yes, I think I hear my Saviour calling me"},
{"Number":"562","Song Title":"On To Calvary","lyrics":"I love to think of my dear Lord"},
{"Number":"563","Song Title":"Jesus Is Mine","lyrics":"Now I have a dear Friend"},
{"Number":"564","Song Title":"Sweet Home","lyrics":"There is a home, a peaceful home"},
{"Number":"565","Song Title":"Marching to That Home","lyrics":"We're marching thru this world below"},
{"Number":"566","Song Title":"O Blessed Day","lyrics":"I have friends beyond the sky"},
{"Number":"567","Song Title":"Child of Thine","lyrics":"Father, I wait before Thy throne"},
{"Number":"568","Song Title":"Gone to Rest","lyrics":"Brother, thou art gone to rest"},
{"Number":"569","Song Title":"He Leads Me All the Way","lyrics":"My Savior leads me ev'ry day"},
{"Number":"570","Song Title":"Our King Above the Sky","lyrics":"Life is the time to serve the Lord"},
{"Number":"571","Song Title":"Not Made With Hands","lyrics":"Christ went a building to prepare"},
{"Number":"572","Song Title":"We Will Sing with Angels There","lyrics":"There is a place called heaven"},
{"Number":"573","Song Title":"Trusting Jesus","lyrics":"Brightly doth His spirit shine"},
{"Number":"574","Song Title":"Sweet Peace","lyrics":"May grace and truth"},
{"Number":"575","Song Title":"Davis (Lonsdale)","lyrics":"Awake, and sing the song"},
{"Number":"576","Song Title":"Allen","lyrics":"O what amazing words of grace"},
{"Number":"577","Song Title":"Forever Blest","lyrics":"Sweet land of rest for thee I sigh"},
{"Number":"578","Song Title":"God’s Wondrous Love","lyrics":"I have heard the gospel message sent to us today"},
{"Number":"580","Song Title":"The Gates of Paradise","lyrics":"Lord Jesus, I'm not worthy"},
{"Number":"581","Song Title":"Wells Second","lyrics":"There is a house not made with hands"},
{"Number":"582","Song Title":"Long Ago, Comrades","lyrics":"Long ago we were boys in the ranks, comrades"},
{"Number":"583","Song Title":"Savannah","lyrics":"From whence does this union arise"},
{"Number":"584","Song Title":"I Love to Sing of Jesus","lyrics":"I love to sing of Jesus"},
{"Number":"585","Song Title":"The Gospel Feast","lyrics":"Come, sinners, to the gospel feast"},
{"Number":"586","Song Title":"Traveler’s Rest—Samson","lyrics":"While trav’ling down life’s weary road"},
{"Number":"587","Song Title":"Nearer, My God, To Thee (Bethany)","lyrics":"Nearer, my God, to Thee"},
{"Number":"588","Song Title":"Worchester","lyrics":"How beauteous are their feet"},
{"Number":"589","Song Title":"Gosia","lyrics":"If I must die, O let me die"},
{"Number":"590","Song Title":"Every Grace","lyrics":"My Savior and my King"},
{"Number":"591","Song Title":"Sweet Reunion","lyrics":"Our fathers who have gone before"},
{"Number":"592","Song Title":"The Judgment","lyrics":"The Lord, the Judge, before His throne"},
{"Number":"594","Song Title":"National Blessings (Glimpse of Thee, A)","lyrics":"Great God of nations now to Thee"}]
